{
  "interactionModel": {
    "languageModel": {
      "intents": [
        {
          "name": "AMAZON.CancelIntent",
          "samples": [
            "ストップ",
            "中断して",
            "キャンセル"
          ]
        },
        {
          "name": "AMAZON.HelpIntent",
          "samples": [
            "使い方を教えて",
            "ヘルプ"
          ]
        },
        {
          "name": "AMAZON.StopIntent",
          "samples": [
            "終了します",
            "終わってください",
            "停止してください",
            "結構です"
          ]
        },
        {
          "name": "AMAZON.NavigateHomeIntent",
          "samples": []
        },
        {
          "slots": [
            {
              "name": "Query",
              "type": "AMAZON.SearchQuery"
            }
          ],
          "name": "QuestionIntent",
          "samples": [
            "テック {Query}",
            "質問 {Query} "
          ]
        }
      ],
      "types": [],
      "invocationName": "テックキュレーター"
    }
  }
}